{"items":{"serializeList":[{"name":"hay","nr":636886.0},{"name":"wood","nr":703737.0},{"name":"carrot","nr":1033158.0},{"name":"pumpkin","nr":1051128.0},{"name":"sunflower_seed","nr":584.0},{"name":"gold","nr":219200.0},{"name":"water_tank","nr":5548.0},{"name":"carrot_seed","nr":1684.0},{"name":"power","nr":340495.9799464719},{"name":"fertilizer","nr":1867.0},{"name":"empty_tank","nr":488.0},{"name":"pumpkin_seed","nr":1304.0}]},"dockedFiles":[],"minimizedFiles":[],"openFilePositions":[{"key":"Pumpkin","value":{"x":-270.95721435546877,"y":732.0707397460938}},{"key":"f1","value":{"x":-1816.1536865234375,"y":311.8217468261719}},{"key":"Sunflowers","value":{"x":-1327.425048828125,"y":638.2431640625}},{"key":"goTo_x_y","value":{"x":-1908.61376953125,"y":1226.5576171875}},{"key":"harvestAll","value":{"x":-1901.895751953125,"y":714.8779907226563}},{"key":"main","value":{"x":-1421.360107421875,"y":1395.930419921875}},{"key":"tradeSeed","value":{"x":-1912.80224609375,"y":1396.8671875}},{"key":"walkMaze","value":{"x":-671.7313232421875,"y":1405.764404296875}}],"openFileSizes":[{"key":"Pumpkin","value":{"x":773.7614135742188,"y":725.5383911132813}},{"key":"f1","value":{"x":500.0,"y":153.23077392578126}},{"key":"Sunflowers","value":{"x":1842.1556396484375,"y":2013.2293701171875}},{"key":"goTo_x_y","value":{"x":500.0,"y":525.2307739257813}},{"key":"harvestAll","value":{"x":672.1004638671875,"y":410.76922607421877}},{"key":"main","value":{"x":856.0413818359375,"y":754.1537475585938}},{"key":"tradeSeed","value":{"x":500.0,"y":181.84616088867188}},{"key":"walkMaze","value":{"x":1165.1561279296875,"y":668.3076782226563}}],"openDocPages":[],"unlocks":["grass","soil","harvest","pass","return","do_a_flip","turf","hay","loops","while","true","false","break","continue","speed","carrots_12","can_harvest","if","else","elif","expand","for","move","north","south","east","west","senses","plant","wood","bush","entities","clear","fertilizer","get_entity_type","get_ground_type","grounds","get_pos_x","get_pos_y","none","num_items","items","variables","range","get_world_size","carrots","debug","carrot","till","can_trade","trade","carrot_seed","operators","and","or","not","lists","print","quick_print","unlocks","cactus_4","assignments","functions","def","watering","empty_tank","water_tank","use_item","get_water","trees","trees_12","tree","pumpkins","sunflowers","pumpkin","pumpkin_seed","speed_20","sunflower_seed","sunflower","power","get_active_power","measure","pumpkins_10","multi_trade","append","remove","pop","insert","len","list","expand_9","utilities","min","max","abs","random","mazes","mazes_5","hedge","treasure","gold","benchmark","get_time","get_op_count","debug_2","set_execution_speed","set_farm_size","cactus","sunflowers_6","swap","cactus_seed","polyculture","get_companion","dictionaries","dicts","sets","add","dict","set","costs","get_cost","auto_unlock","unlock","num_unlocked","grass_12"],"grounds":[{"pos":{"x":0,"y":0},"data":"type = soil,water = 0.580796291086879"},{"pos":{"x":0,"y":1},"data":"type = soil,water = 0.560017703509722"},{"pos":{"x":0,"y":2},"data":"type = soil,water = 0.713228721868931"},{"pos":{"x":0,"y":3},"data":"type = soil,water = 0.536318304885922"},{"pos":{"x":0,"y":4},"data":"type = soil,water = 0.664000684969586"},{"pos":{"x":0,"y":5},"data":"type = soil,water = 0.565562455627149"},{"pos":{"x":0,"y":6},"data":"type = soil,water = 0.718472447879695"},{"pos":{"x":0,"y":7},"data":"type = soil,water = 0.745807191015769"},{"pos":{"x":0,"y":8},"data":"type = soil,water = 0.619819802803647"},{"pos":{"x":0,"y":9},"data":"type = soil,water = 0.674694874272381"},{"pos":{"x":1,"y":0},"data":"type = soil,water = 0.728205576356933"},{"pos":{"x":1,"y":1},"data":"type = soil,water = 0.502905263942742"},{"pos":{"x":1,"y":2},"data":"type = soil,water = 0.661552044855107"},{"pos":{"x":1,"y":3},"data":"type = soil,water = 0.533183557442455"},{"pos":{"x":1,"y":4},"data":"type = soil,water = 0.671087794699706"},{"pos":{"x":1,"y":5},"data":"type = soil,water = 0.57429934646607"},{"pos":{"x":1,"y":6},"data":"type = soil,water = 0.72119525679674"},{"pos":{"x":1,"y":7},"data":"type = soil,water = 0.556466082462944"},{"pos":{"x":1,"y":8},"data":"type = soil,water = 0.526140333835706"},{"pos":{"x":1,"y":9},"data":"type = soil,water = 0.684198602892599"},{"pos":{"x":2,"y":0},"data":"type = soil,water = 0.505485592693254"},{"pos":{"x":2,"y":1},"data":"type = soil,water = 0.519800454841358"},{"pos":{"x":2,"y":2},"data":"type = soil,water = 0.60314242713604"},{"pos":{"x":2,"y":3},"data":"type = soil,water = 0.506452978921927"},{"pos":{"x":2,"y":4},"data":"type = soil,water = 0.501107652966342"},{"pos":{"x":2,"y":5},"data":"type = soil,water = 0.506477501338947"},{"pos":{"x":2,"y":6},"data":"type = soil,water = 0.650998130541713"},{"pos":{"x":2,"y":7},"data":"type = soil,water = 0.688658056117062"},{"pos":{"x":2,"y":8},"data":"type = soil,water = 0.56488872189389"},{"pos":{"x":2,"y":9},"data":"type = soil,water = 0.503851931638951"},{"pos":{"x":3,"y":0},"data":"type = soil,water = 0.509139620270195"},{"pos":{"x":3,"y":1},"data":"type = soil,water = 0.567517350043721"},{"pos":{"x":3,"y":2},"data":"type = soil,water = 0.569295504738142"},{"pos":{"x":3,"y":3},"data":"type = soil,water = 0.517745236761415"},{"pos":{"x":3,"y":4},"data":"type = soil,water = 0.491160555264423"},{"pos":{"x":3,"y":5},"data":"type = soil,water = 0.72352060735895"},{"pos":{"x":3,"y":6},"data":"type = soil,water = 0.501485022113534"},{"pos":{"x":3,"y":7},"data":"type = soil,water = 0.667283726462674"},{"pos":{"x":3,"y":8},"data":"type = soil,water = 0.676336048436036"},{"pos":{"x":3,"y":9},"data":"type = soil,water = 0.714058617060368"},{"pos":{"x":4,"y":0},"data":"type = soil,water = 0.547038179789327"},{"pos":{"x":4,"y":1},"data":"type = soil,water = 0.548717358082246"},{"pos":{"x":4,"y":2},"data":"type = soil,water = 0.535569152308758"},{"pos":{"x":4,"y":3},"data":"type = soil,water = 0.6809764739117"},{"pos":{"x":4,"y":4},"data":"type = soil,water = 0.48670494323987"},{"pos":{"x":4,"y":5},"data":"type = soil,water = 0.495518989627636"},{"pos":{"x":4,"y":6},"data":"type = soil,water = 0.542235730938403"},{"pos":{"x":4,"y":7},"data":"type = soil,water = 0.502114546834599"},{"pos":{"x":4,"y":8},"data":"type = soil,water = 0.50438956807098"},{"pos":{"x":4,"y":9},"data":"type = soil,water = 0.579803006955208"},{"pos":{"x":5,"y":0},"data":"type = soil,water = 0.705022204899289"},{"pos":{"x":5,"y":1},"data":"type = soil,water = 0.691716845772485"},{"pos":{"x":5,"y":2},"data":"type = soil,water = 0.69862950144263"},{"pos":{"x":5,"y":3},"data":"type = soil,water = 0.557401456471138"},{"pos":{"x":5,"y":4},"data":"type = soil,water = 0.722931521810188"},{"pos":{"x":5,"y":5},"data":"type = soil,water = 0.510078310845838"},{"pos":{"x":5,"y":6},"data":"type = soil,water = 0.657964924212707"},{"pos":{"x":5,"y":7},"data":"type = soil,water = 0.551950921679765"},{"pos":{"x":5,"y":8},"data":"type = soil,water = 0.511024515644734"},{"pos":{"x":5,"y":9},"data":"type = soil,water = 0.728431205749505"},{"pos":{"x":6,"y":0},"data":"type = soil,water = 0.575833111175588"},{"pos":{"x":6,"y":1},"data":"type = soil,water = 0.665801212107022"},{"pos":{"x":6,"y":2},"data":"type = soil,water = 0.647905678986686"},{"pos":{"x":6,"y":3},"data":"type = soil,water = 0.546082691041085"},{"pos":{"x":6,"y":4},"data":"type = soil,water = 0.516153708161091"},{"pos":{"x":6,"y":5},"data":"type = soil,water = 0.559003027718697"},{"pos":{"x":6,"y":6},"data":"type = soil,water = 0.605103871256352"},{"pos":{"x":6,"y":7},"data":"type = soil,water = 0.505973156668998"},{"pos":{"x":6,"y":8},"data":"type = soil,water = 0.560055741890561"},{"pos":{"x":6,"y":9},"data":"type = soil,water = 0.717901190032683"},{"pos":{"x":7,"y":0},"data":"type = soil,water = 0.729292969954428"},{"pos":{"x":7,"y":1},"data":"type = soil,water = 0.552263763404434"},{"pos":{"x":7,"y":2},"data":"type = soil,water = 0.73349632788484"},{"pos":{"x":7,"y":3},"data":"type = soil,water = 0.712751824573507"},{"pos":{"x":7,"y":4},"data":"type = soil,water = 0.641764695860102"},{"pos":{"x":7,"y":5},"data":"type = soil,water = 0.511633286302618"},{"pos":{"x":7,"y":6},"data":"type = soil,water = 0.551197741194007"},{"pos":{"x":7,"y":7},"data":"type = soil,water = 0.560854236964266"},{"pos":{"x":7,"y":8},"data":"type = soil,water = 0.537988107547961"},{"pos":{"x":7,"y":9},"data":"type = soil,water = 0.57241104826711"},{"pos":{"x":8,"y":0},"data":"type = soil,water = 0.694586824250837"},{"pos":{"x":8,"y":1},"data":"type = soil,water = 0.565791367796868"},{"pos":{"x":8,"y":2},"data":"type = soil,water = 0.533967914904084"},{"pos":{"x":8,"y":3},"data":"type = soil,water = 0.734429422273739"},{"pos":{"x":8,"y":4},"data":"type = soil,water = 0.503644613715286"},{"pos":{"x":8,"y":5},"data":"type = soil,water = 0.728888002611173"},{"pos":{"x":8,"y":6},"data":"type = soil,water = 0.530091563466367"},{"pos":{"x":8,"y":7},"data":"type = soil,water = 0.509761502928176"},{"pos":{"x":8,"y":8},"data":"type = soil,water = 0.531924981507535"},{"pos":{"x":8,"y":9},"data":"type = soil,water = 0.548602519500226"},{"pos":{"x":9,"y":0},"data":"type = soil,water = 0.561297602607458"},{"pos":{"x":9,"y":1},"data":"type = soil,water = 0.738451509563791"},{"pos":{"x":9,"y":2},"data":"type = soil,water = 0.582133018364622"},{"pos":{"x":9,"y":3},"data":"type = soil,water = 0.512474257960207"},{"pos":{"x":9,"y":4},"data":"type = soil,water = 0.540835659689994"},{"pos":{"x":9,"y":5},"data":"type = soil,water = 0.562545169231148"},{"pos":{"x":9,"y":6},"data":"type = soil,water = 0.509349804922116"},{"pos":{"x":9,"y":7},"data":"type = soil,water = 0.540741742829252"},{"pos":{"x":9,"y":8},"data":"type = soil,water = 0.560092994102715"},{"pos":{"x":9,"y":9},"data":"type = soil,water = 0.737461432290244"}],"entities":[{"pos":{"x":5,"y":6},"data":"type = grass,growth stage = 1,grown percent = 0"},{"pos":{"x":6,"y":1},"data":"type = grass,growth stage = 1,grown percent = 0"},{"pos":{"x":1,"y":5},"data":"type = grass,growth stage = 1,grown percent = 0"},{"pos":{"x":1,"y":3},"data":"type = grass,growth stage = 1,grown percent = 0"},{"pos":{"x":7,"y":2},"data":"type = grass,growth stage = 1,grown percent = 0"},{"pos":{"x":1,"y":2},"data":"type = grass,growth stage = 0,grown percent = 0"},{"pos":{"x":1,"y":7},"data":"type = grass,growth stage = 1,grown percent = 0"},{"pos":{"x":5,"y":7},"data":"type = grass,growth stage = 1,grown percent = 0"},{"pos":{"x":9,"y":7},"data":"type = carrots,growth stage = 0,grown percent = 0,239821374693433"},{"pos":{"x":9,"y":2},"data":"type = carrots,growth stage = 0,grown percent = 0,189129934029746"},{"pos":{"x":3,"y":1},"data":"type = grass,growth stage = 1,grown percent = 0"},{"pos":{"x":7,"y":6},"data":"type = grass,growth stage = 1,grown percent = 0"},{"pos":{"x":6,"y":9},"data":"type = grass,growth stage = 1,grown percent = 0"},{"pos":{"x":7,"y":8},"data":"type = grass,growth stage = 1,grown percent = 0"},{"pos":{"x":7,"y":7},"data":"type = tree,growth stage = 0,grown percent = 0,253219180518403"},{"pos":{"x":0,"y":1},"data":"type = grass,growth stage = 1,grown percent = 0"},{"pos":{"x":5,"y":3},"data":"type = grass,growth stage = 1,grown percent = 0"},{"pos":{"x":2,"y":8},"data":"type = grass,growth stage = 1,grown percent = 0"},{"pos":{"x":8,"y":9},"data":"type = grass,growth stage = 1,grown percent = 0"},{"pos":{"x":2,"y":3},"data":"type = grass,growth stage = 1,grown percent = 0"},{"pos":{"x":6,"y":0},"data":"type = grass,growth stage = 1,grown percent = 0"},{"pos":{"x":2,"y":4},"data":"type = grass,growth stage = 1,grown percent = 0"},{"pos":{"x":4,"y":7},"data":"type = grass,growth stage = 1,grown percent = 0"},{"pos":{"x":3,"y":4},"data":"type = grass,growth stage = 1,grown percent = 0"},{"pos":{"x":4,"y":0},"data":"type = grass,growth stage = 1,grown percent = 0"},{"pos":{"x":2,"y":5},"data":"type = grass,growth stage = 1,grown percent = 0"},{"pos":{"x":7,"y":0},"data":"type = grass,growth stage = 1,grown percent = 0"},{"pos":{"x":5,"y":2},"data":"type = grass,growth stage = 1,grown percent = 0"},{"pos":{"x":8,"y":1},"data":"type = grass,growth stage = 1,grown percent = 0"},{"pos":{"x":2,"y":2},"data":"type = tree,growth stage = 1,grown percent = 0"},{"pos":{"x":3,"y":6},"data":"type = grass,growth stage = 1,grown percent = 0"},{"pos":{"x":4,"y":4},"data":"type = tree,growth stage = 1,grown percent = 0"},{"pos":{"x":3,"y":9},"data":"type = grass,growth stage = 1,grown percent = 0"},{"pos":{"x":6,"y":4},"data":"type = grass,growth stage = 1,grown percent = 0"},{"pos":{"x":9,"y":9},"data":"type = tree,growth stage = 0,grown percent = 0,193475710841522"},{"pos":{"x":7,"y":4},"data":"type = grass,growth stage = 1,grown percent = 0"},{"pos":{"x":0,"y":0},"data":"type = tree,growth stage = 0,grown percent = 0,052284506250441"},{"pos":{"x":0,"y":2},"data":"type = grass,growth stage = 1,grown percent = 0"},{"pos":{"x":3,"y":7},"data":"type = grass,growth stage = 1,grown percent = 0"},{"pos":{"x":5,"y":5},"data":"type = tree,growth stage = 1,grown percent = 0"},{"pos":{"x":2,"y":0},"data":"type = grass,growth stage = 1,grown percent = 0"},{"pos":{"x":5,"y":4},"data":"type = grass,growth stage = 1,grown percent = 0"},{"pos":{"x":0,"y":4},"data":"type = grass,growth stage = 1,grown percent = 0"},{"pos":{"x":0,"y":5},"data":"type = grass,growth stage = 1,grown percent = 0"},{"pos":{"x":0,"y":8},"data":"type = grass,growth stage = 1,grown percent = 0"},{"pos":{"x":4,"y":5},"data":"type = grass,growth stage = 1,grown percent = 0"},{"pos":{"x":3,"y":8},"data":"type = grass,growth stage = 1,grown percent = 0"},{"pos":{"x":6,"y":6},"data":"type = tree,growth stage = 1,grown percent = 0"},{"pos":{"x":6,"y":5},"data":"type = grass,growth stage = 1,grown percent = 0"},{"pos":{"x":1,"y":6},"data":"type = grass,growth stage = 1,grown percent = 0"},{"pos":{"x":5,"y":8},"data":"type = grass,growth stage = 1,grown percent = 0"},{"pos":{"x":2,"y":9},"data":"type = grass,growth stage = 1,grown percent = 0"},{"pos":{"x":2,"y":1},"data":"type = grass,growth stage = 1,grown percent = 0"},{"pos":{"x":6,"y":7},"data":"type = grass,growth stage = 1,grown percent = 0"},{"pos":{"x":4,"y":1},"data":"type = grass,growth stage = 1,grown percent = 0"},{"pos":{"x":7,"y":9},"data":"type = grass,growth stage = 1,grown percent = 0"},{"pos":{"x":9,"y":5},"data":"type = carrots,growth stage = 0,grown percent = 0"},{"pos":{"x":3,"y":3},"data":"type = tree,growth stage = 1,grown percent = 0"},{"pos":{"x":9,"y":0},"data":"type = carrots,growth stage = 0,grown percent = 0"},{"pos":{"x":8,"y":7},"data":"type = grass,growth stage = 1,grown percent = 0"},{"pos":{"x":6,"y":3},"data":"type = grass,growth stage = 1,grown percent = 0"},{"pos":{"x":0,"y":6},"data":"type = grass,growth stage = 1,grown percent = 0"},{"pos":{"x":4,"y":3},"data":"type = grass,growth stage = 1,grown percent = 0"},{"pos":{"x":6,"y":2},"data":"type = grass,growth stage = 1,grown percent = 0"},{"pos":{"x":7,"y":5},"data":"type = grass,growth stage = 1,grown percent = 0"},{"pos":{"x":9,"y":4},"data":"type = carrots,growth stage = 0,grown percent = 0,0185226246835822"},{"pos":{"x":8,"y":8},"data":"type = tree,growth stage = 0,grown percent = 0,190894261943364"},{"pos":{"x":9,"y":1},"data":"type = carrots,growth stage = 0,grown percent = 0,157294744563293"},{"pos":{"x":8,"y":5},"data":"type = grass,growth stage = 1,grown percent = 0"},{"pos":{"x":2,"y":7},"data":"type = grass,growth stage = 1,grown percent = 0"},{"pos":{"x":1,"y":8},"data":"type = grass,growth stage = 1,grown percent = 0"},{"pos":{"x":4,"y":2},"data":"type = grass,growth stage = 1,grown percent = 0"},{"pos":{"x":4,"y":9},"data":"type = grass,growth stage = 1,grown percent = 0"},{"pos":{"x":9,"y":8},"data":"type = carrots,growth stage = 0,grown percent = 0,0322733309608228"},{"pos":{"x":9,"y":3},"data":"type = carrots,growth stage = 0,grown percent = 0,144032218925351"},{"pos":{"x":9,"y":6},"data":"type = carrots,growth stage = 0,grown percent = 0,2238478427544"},{"pos":{"x":1,"y":1},"data":"type = tree,growth stage = 0,grown percent = 0"},{"pos":{"x":6,"y":8},"data":"type = grass,growth stage = 1,grown percent = 0"},{"pos":{"x":1,"y":9},"data":"type = grass,growth stage = 1,grown percent = 0"},{"pos":{"x":3,"y":0},"data":"type = grass,growth stage = 1,grown percent = 0"},{"pos":{"x":5,"y":1},"data":"type = grass,growth stage = 1,grown percent = 0"},{"pos":{"x":7,"y":1},"data":"type = grass,growth stage = 1,grown percent = 0"},{"pos":{"x":4,"y":8},"data":"type = grass,growth stage = 1,grown percent = 0"},{"pos":{"x":1,"y":0},"data":"type = grass,growth stage = 0,grown percent = 0"},{"pos":{"x":4,"y":6},"data":"type = grass,growth stage = 1,grown percent = 0"},{"pos":{"x":5,"y":0},"data":"type = grass,growth stage = 1,grown percent = 0"},{"pos":{"x":3,"y":2},"data":"type = grass,growth stage = 1,grown percent = 0"},{"pos":{"x":0,"y":7},"data":"type = grass,growth stage = 1,grown percent = 0"},{"pos":{"x":0,"y":9},"data":"type = grass,growth stage = 1,grown percent = 0"},{"pos":{"x":1,"y":4},"data":"type = grass,growth stage = 1,grown percent = 0"},{"pos":{"x":0,"y":3},"data":"type = grass,growth stage = 1,grown percent = 0"},{"pos":{"x":5,"y":9},"data":"type = grass,growth stage = 1,grown percent = 0"},{"pos":{"x":3,"y":5},"data":"type = grass,growth stage = 1,grown percent = 0"},{"pos":{"x":2,"y":6},"data":"type = grass,growth stage = 1,grown percent = 0"},{"pos":{"x":8,"y":3},"data":"type = grass,growth stage = 1,grown percent = 0"},{"pos":{"x":8,"y":4},"data":"type = grass,growth stage = 1,grown percent = 0"},{"pos":{"x":8,"y":2},"data":"type = grass,growth stage = 1,grown percent = 0"},{"pos":{"x":7,"y":3},"data":"type = grass,growth stage = 1,grown percent = 0"},{"pos":{"x":8,"y":0},"data":"type = grass,growth stage = 1,grown percent = 0"},{"pos":{"x":8,"y":6},"data":"type = grass,growth stage = 1,grown percent = 0"}]}